pyperclip3/__init__.py
pyperclip3/__main__.py
pyperclip3/base.py
pyperclip3/cli.py
pyperclip3/macos_clip.py
pyperclip3/util.py
pyperclip3/win_clip.py
pyperclip3/xclip_clip.py
pyperclip3-0.4.1.dist-info/LICENSE
pyperclip3-0.4.1.dist-info/METADATA
pyperclip3-0.4.1.dist-info/WHEEL
pyperclip3-0.4.1.dist-info/entry_points.txt
pyperclip3-0.4.1.dist-info/top_level.txt
pyperclip3-0.4.1.dist-info/RECORD
