Metadata-Version: 2.1
Name: pyperclip3
Version: 0.4.1
Summary: Cross-platform clipboard utilities supporting both binary and text data.
Home-page: https://github.com/spyoungtech/pyclip
Author: Spencer Young
Author-email: spencer.young@spyoung.com
License: Apache
Keywords: pyperclip clipboard cross-platform binary bytes files
Platform: UNKNOWN
Classifier: Intended Audience :: Developers
Classifier: Programming Language :: Python
Classifier: License :: OSI Approved :: Apache Software License
Classifier: Programming Language :: Python :: 3 :: Only
Classifier: Programming Language :: Python :: 3.7
Classifier: Programming Language :: Python :: 3.8
Classifier: Programming Language :: Python :: 3.9
Provides-Extra: test
